Metadata-Version: 2.1
Name: arvia
Version: 0.3.4
Summary: ARVIA (Antibiotic Resistance Variant Identifier for Pseudomonas aeruginosa) takes single-end/paired-end reads and/or assemblies to perform exhaustive variant calling of genes related to antibiotic resistance in Pseudomonas aeruginosa.
Author-email: Pablo Aja <paabloaja@gmail.com>
Project-URL: Homepage, https://github.com/pablo-aja-macaya/ARVIA
Project-URL: Issues, https://github.com/pablo-aja-macaya/ARVIA/issues
Classifier: Development Status :: 4 - Beta
Classifier: Intended Audience :: Science/Research
Classifier: License :: OSI Approved :: GNU General Public License v3 (GPLv3)
Classifier: Operating System :: POSIX :: Linux
Classifier: Programming Language :: Python :: 3.8
Classifier: Natural Language :: English
Classifier: Topic :: Scientific/Engineering :: Bio-Informatics
Requires-Python: <3.9,>=3.8
License-File: LICENSE.md
Requires-Dist: snakemake==7.18.0
Requires-Dist: pandas==1.5.0
Requires-Dist: numpy==1.23.1
Requires-Dist: odfpy==1.4.1
Requires-Dist: colorama==0.4.4
Requires-Dist: biopython>=1.78
Requires-Dist: rich-argparse==1.6.0
Requires-Dist: toml==0.10.2
Requires-Dist: openpyxl==3.1
Requires-Dist: xlsxwriter
